Metadata-Version: 2.1
Name: fastq-preprocessor
Version: 2023.7.24
Summary: Fast short read fastq preprocessor with optional contamination removal
Home-page: https://github.com/jolespin/fastq_preprocessor
Author: Josh L. Espinoza
Author-email: jespinoz@jcvi.org
License: GNU AFFERO GENERAL PUBLIC LICENSE
License-File: LICENSE
